README.rst
pyproject.toml
setup.cfg
setup.py
django_ns_ratelimit.egg-info/PKG-INFO
django_ns_ratelimit.egg-info/SOURCES.txt
django_ns_ratelimit.egg-info/dependency_links.txt
django_ns_ratelimit.egg-info/requires.txt
django_ns_ratelimit.egg-info/top_level.txt
ratelimit/__init__.py
ratelimit/decorators.py
ratelimit/middleware.py